mongodb_connect/__init__.py
mongodb_connect/mongo_crud.py
customdboperations-0.0.2.dist-info/LICENSE
customdboperations-0.0.2.dist-info/METADATA
customdboperations-0.0.2.dist-info/WHEEL
customdboperations-0.0.2.dist-info/top_level.txt
customdboperations-0.0.2.dist-info/RECORD
